new_python_project/__init__.py
new_python_project/__main__.py
new_python_project/warnings_util.py
new_python_project/template/.gitignore
new_python_project/template/COPYING
new_python_project/template/Makefile
new_python_project/template/README.nancy.md
new_python_project/template/author.in.py
new_python_project/template/description.in.py
new_python_project/template/email.in.py
new_python_project/template/project_executable.in.py
new_python_project/template/project_home_page.in.py
new_python_project/template/project_module.in.py
new_python_project/template/project_name.in.py
new_python_project/template/pyproject.nancy.toml
new_python_project/template/year.in.py
new_python_project/template/$run(project_module.in.py)/__init__.nancy.py
new_python_project/template/$run(project_module.in.py)/__main__.nancy.py
new_python_project/template/$run(project_module.in.py)/warnings_util.py
new_python_project/template/$run(project_module.in.py)/subcommand/__init__.nancy.py
new_python_project/template/$run(project_module.in.py)/subcommand/demo.py
new_python_project/template/.github/workflows/ci.nancy.yml
new_python_project/template/tests/.gitignore
new_python_project/template/tests/conftest.py
new_python_project/template/tests/test_$run(project_module.in.py).nancy.py
new_python_project/template/tests/testutils.nancy.py
new_python_project/template/tests/__pycache__/conftest.cpython-312-pytest-8.3.3.pyc
new_python_project/template/tests/__pycache__/conftest.cpython-312-pytest-8.3.5.pyc
new_python_project/template/tests/test-files/greeting-goodbye-expected.nancy.txt
new_python_project-0.3.0.dist-info/licenses/COPYING
new_python_project-0.3.0.dist-info/METADATA
new_python_project-0.3.0.dist-info/WHEEL
new_python_project-0.3.0.dist-info/entry_points.txt
new_python_project-0.3.0.dist-info/top_level.txt
new_python_project-0.3.0.dist-info/RECORD
