Metadata-Version: 2.4
Name: new-python-project
Version: 0.3.0
Summary: Create a Python project from a simple template
Author-email: Reuben Thomas <rrt@sc3d.org>
License-Expression: GPL-3.0-or-later
Project-URL: Homepage, https://github.com/rrthomas/python_project
Classifier: Environment :: Console
Classifier: Programming Language :: Python :: 3
Requires-Python: >=3.12
License-File: COPYING
Requires-Dist: nancy~=11.0
Provides-Extra: test
Requires-Dist: pytest; extra == "test"
Dynamic: license-file
